matchpoint/__init__.py
matchpoint/_version.py
matchpoint/coordinate_transformations.py
matchpoint/core.py
matchpoint/cross_correlation.py
matchpoint/decorators.py
matchpoint/geometric_hashing.py
matchpoint/icp.py
matchpoint/kernel_correlation.py
matchpoint/point_set.py
matchpoint/point_set_simulation.py
matchpoint/polynomial.py
matchpoint/polywarp.py
matchpoint-1.0.4.dist-info/licenses/LICENSE
matchpoint-1.0.4.dist-info/METADATA
matchpoint-1.0.4.dist-info/WHEEL
matchpoint-1.0.4.dist-info/top_level.txt
matchpoint-1.0.4.dist-info/RECORD
